dashboard/dashboard.py
raptor/__init__.py
raptor/automated_reporting.py
raptor/benchmark.py
raptor/cli.py
raptor/cloud_integration.py
raptor/data_quality_assessment.py
raptor/ensemble_analysis.py
raptor/example_ml_workflow.py
raptor/example_quality_assessment.py
raptor/ml_recommender.py
raptor/parameter_optimization.py
raptor/profiler.py
raptor/raptor_ml_cli.py
raptor/recommender.py
raptor/report.py
raptor/resource_monitoring.py
raptor/simulate.py
raptor/synthetic_benchmarks.py
raptor/test_raptor_v2_1_0.py
raptor/utils.py
raptor/threshold_optimizer/__init__.py
raptor/threshold_optimizer/ato.py
raptor/threshold_optimizer/visualization.py
raptor_rnaseq-2.1.2.dist-info/licenses/LICENSE
scripts/01_run_all_pipelines_python.py
scripts/02_profile_data.py
scripts/05_ml_recommendation.py
scripts/06_quality_assessment.py
scripts/07_ensemble_analysis.py
scripts/08_automated_report.py
scripts/09_resource_monitoring.py
scripts/10_parameter_optimization.py
scripts/11_threshold_optimizer.py
raptor_rnaseq-2.1.2.dist-info/METADATA
raptor_rnaseq-2.1.2.dist-info/WHEEL
raptor_rnaseq-2.1.2.dist-info/entry_points.txt
raptor_rnaseq-2.1.2.dist-info/top_level.txt
raptor_rnaseq-2.1.2.dist-info/RECORD
