Metadata-Version: 2.4
Name: raptor-rnaseq
Version: 2.1.2
Summary: RNA-seq Analysis Pipeline Testing and Optimization Resource with ML-powered recommendations and adaptive threshold optimization
Home-page: https://github.com/AyehBlk/RAPTOR
Author: Ayeh Bolouki
Author-email: Ayeh Bolouki <ayehbolouki1988@gmail.com>
Maintainer-email: Ayeh Bolouki <ayehbolouki1988@gmail.com>
License: MIT
Project-URL: Homepage, https://github.com/AyehBlk/RAPTOR
Project-URL: Documentation, https://github.com/AyehBlk/RAPTOR/tree/main/docs
Project-URL: Repository, https://github.com/AyehBlk/RAPTOR
Project-URL: Bug Tracker, https://github.com/AyehBlk/RAPTOR/issues
Project-URL: Changelog, https://github.com/AyehBlk/RAPTOR/blob/main/docs/CHANGELOG.md
Keywords: rna-seq,differential-expression,bioinformatics,computational-biology,transcriptomics,pipeline,benchmarking,data-analysis,genomics,machine-learning,quality-assessment,data-quality,dashboard,interactive,threshold-optimization,adaptive-threshold
Classifier: Development Status :: 4 - Beta
Classifier: Intended Audience :: Science/Research
Classifier: Intended Audience :: Developers
Classifier: Topic :: Scientific/Engineering :: Bio-Informatics
Classifier: Topic :: Scientific/Engineering :: Artificial Intelligence
Classifier: Topic :: Software Development :: Libraries :: Python Modules
Classifier: License :: OSI Approved :: MIT License
Classifier: Programming Language :: Python :: 3
Classifier: Programming Language :: Python :: 3.8
Classifier: Programming Language :: Python :: 3.9
Classifier: Programming Language :: Python :: 3.10
Classifier: Programming Language :: Python :: 3.11
Classifier: Programming Language :: Python :: 3.12
Classifier: Operating System :: OS Independent
Classifier: Operating System :: POSIX :: Linux
Classifier: Operating System :: MacOS
Classifier: Natural Language :: English
Requires-Python: >=3.8
License-File: LICENSE
Requires-Dist: numpy>=1.21.0
Requires-Dist: pandas>=1.3.0
Requires-Dist: scipy>=1.7.0
Requires-Dist: matplotlib>=3.4.0
Requires-Dist: seaborn>=0.11.0
Requires-Dist: scikit-learn>=1.0.0
Requires-Dist: joblib>=1.1.0
Requires-Dist: pyyaml>=5.4.0
Requires-Dist: jinja2>=3.0.0
Requires-Dist: click>=8.0.0
Requires-Dist: tqdm>=4.62.0
Requires-Dist: colorama>=0.4.4
Requires-Dist: statsmodels>=0.13.0
Provides-Extra: ml
Requires-Dist: scikit-learn>=1.0.0; extra == "ml"
Requires-Dist: joblib>=1.1.0; extra == "ml"
Provides-Extra: dashboard
Requires-Dist: streamlit>=1.28.0; extra == "dashboard"
Requires-Dist: plotly>=5.14.0; extra == "dashboard"
Requires-Dist: psutil>=5.8.0; extra == "dashboard"
Provides-Extra: advanced
Requires-Dist: bayesian-optimization>=1.2.0; extra == "advanced"
Requires-Dist: markdown>=3.3.0; extra == "advanced"
Requires-Dist: weasyprint>=52.5; extra == "advanced"
Requires-Dist: colorlog>=6.6.0; extra == "advanced"
Provides-Extra: dev
Requires-Dist: pytest>=7.0.0; extra == "dev"
Requires-Dist: pytest-cov>=3.0.0; extra == "dev"
Requires-Dist: black>=22.0.0; extra == "dev"
Requires-Dist: flake8>=4.0.0; extra == "dev"
Requires-Dist: mypy>=0.950; extra == "dev"
Requires-Dist: sphinx>=4.0.0; extra == "dev"
Requires-Dist: sphinx_rtd_theme>=1.0.0; extra == "dev"
Provides-Extra: docs
Requires-Dist: sphinx>=4.0.0; extra == "docs"
Requires-Dist: sphinx_rtd_theme>=1.0.0; extra == "docs"
Requires-Dist: sphinx-click>=3.0.0; extra == "docs"
Provides-Extra: all
Requires-Dist: scikit-learn>=1.0.0; extra == "all"
Requires-Dist: joblib>=1.1.0; extra == "all"
Requires-Dist: streamlit>=1.28.0; extra == "all"
Requires-Dist: plotly>=5.14.0; extra == "all"
Requires-Dist: psutil>=5.8.0; extra == "all"
Requires-Dist: bayesian-optimization>=1.2.0; extra == "all"
Requires-Dist: markdown>=3.3.0; extra == "all"
Requires-Dist: weasyprint>=52.5; extra == "all"
Requires-Dist: colorlog>=6.6.0; extra == "all"
Requires-Dist: pytest>=7.0.0; extra == "all"
Requires-Dist: pytest-cov>=3.0.0; extra == "all"
Requires-Dist: black>=22.0.0; extra == "all"
Requires-Dist: flake8>=4.0.0; extra == "all"
Requires-Dist: mypy>=0.950; extra == "all"
Requires-Dist: sphinx>=4.0.0; extra == "all"
Requires-Dist: sphinx_rtd_theme>=1.0.0; extra == "all"
Requires-Dist: sphinx-click>=3.0.0; extra == "all"
Dynamic: author
Dynamic: home-page
Dynamic: license-file
Dynamic: requires-python
